day5/dvsd_pe.v
module dvsd_pe (in, out, en, eno, gs, clk);

	input en, clk;
	input [7:0] in;
	output reg [2:0] out;
	output reg eno, gs;
	
	reg _a_;
	
	always @ (posedge clk or negedge clk)
		begin
			_a_ = ~& in ;
			eno = ~(_a_ & en);
			gs = ~eno & en;
		end
			
	always @ (posedge clk or negedge clk)
		begin
			if (en)
			casex (in)
				// Highest Priority
				8'bxxxxxxx1: out = 3'b000;
				8'bxxxxxx1x: out = 3'b001;
				8'bxxxxx1xx: out = 3'b010;
				8'bxxxx1xxx: out = 3'b011;
				8'bxxx1xxxx: out = 3'b100;
				8'bxx1xxxxx: out = 3'b101;
				8'bx1xxxxxx: out = 3'b110;
				8'b1xxxxxxx: out = 3'b111;
				// Lowest Priority
				default : out = 1'bx;
			endcase
		end
		
endmodule

day5/test_dvsd_pe.v

`timescale 1ns / 1ps
`include "dvsd_pe.v"

module test_dvsd_pe;

	reg en, clk;
	reg [7:0] in;
	
 	wire eno, gs;
	wire [2:0] out;
	

 dvsd_pe DUT (.in(in), .en(en), .out(out), .eno(eno), .gs(gs), .clk(clk));

initial
	begin
		$monitor ($time, " en=%4b, in=%8b, out=%3b, eno=%4b, gs=%4b", en, in, out, eno, gs);
		$dumpfile("dvsd_pe.vcd");	
		$dumpvars(0,test_dvsd_pe);
		
		clk = 1;
		forever #5 clk = ~clk;
	end
	
initial
	begin	
		in = 8'b00000000; en = 0; #5;
		in = 8'b00000001; en = 1; #5;
		in = 8'b00100010; en = 1; #5;
		in = 8'b10000100; en = 1; #5;
		in = 8'b00001000; en = 1; #5;
		in = 8'b00010000; en = 1; #5;
		in = 8'b00100000; en = 1; #5;
		in = 8'b01000000; en = 1; #5;
		in = 8'b10001000; en = 1; #5;
		in = 5'b00000; en = 1; 
	end
initial 
	#50 $finish;
endmodule

day5/dvsd_pe.vcd
$date
	Mon Dec  6 11:25:54 2021
$end
$version
	Icarus Verilog
$end
$timescale
	1ps
$end
$scope module test_dvsd_pe $end
$var wire 3 ! out [2:0] $end
$var wire 1 " gs $end
$var wire 1 # eno $end
$var reg 1 $ clk $end
$var reg 1 % en $end
$var reg 8 & in [7:0] $end
$scope module DUT $end
$var wire 1 $ clk $end
$var wire 1 % en $end
$var wire 8 ' in [7:0] $end
$var reg 1 ( _a_ $end
$var reg 1 # eno $end
$var reg 1 " gs $end
$var reg 3 ) out [2:0] $end
$upscope $end
$upscope $end
$enddefinitions $end
#0
$dumpvars
bx )
1(
b0 '
b0 &
0%
1$
1#
0"
bx !
$end
#5000
b0 !
b0 )
1"
0#
1%
b1 &
b1 '
0$
#10000
b1 !
b1 )
b100010 &
b100010 '
1$
#15000
b10 !
b10 )
b10000100 &
b10000100 '
0$
#20000
b11 !
b11 )
b1000 &
b1000 '
1$
#25000
b100 !
b100 )
b10000 &
b10000 '
0$
#30000
b101 !
b101 )
b100000 &
b100000 '
1$
#35000
b110 !
b110 )
b1000000 &
b1000000 '
0$
#40000
b11 !
b11 )
b10001000 &
b10001000 '
1$
#45000
b0x !
b0x )
b0 &
b0 '
0$
